<?xml version='1.0' encoding='UTF-8'?>
<data>
	<info>
		<savetime>14:04:00 11-09-2013</savetime>
		<progress>completed</progress>
	</info>
	<schema path="./" protocol="file">temporal.schema.xml</schema>
	<annotations>
		<entity>
			<id>65@e@doc0057_PATH@gold</id>
			<span>27,36</span>
			<type>Event</type>
			</entity>
		<entity>
			<id>66@e@doc0057_PATH@gold</id>
			<span>67,73</span>
			<type>Event</type>
			</entity>
		<entity>
			<id>67@e@doc0057_PATH@gold</id>
			<span>75,83</span>
			<type>Event</type>
			</entity>
		<entity>
			<id>68@e@doc0057_PATH@gold</id>
			<span>84,93</span>
			<type>Event</type>
			</entity>
		<entity>
			<id>69@e@doc0057_PATH@gold</id>
			<span>107,116</span>
			<type>Event</type>
			</entity>
		<entity>
			<id>70@e@doc0057_PATH@gold</id>
			<span>283,292</span>
			<type>Event</type>
			</entity>
		<entity>
			<id>71@e@doc0057_PATH@gold</id>
			<span>324,332</span>
			<type>Event</type>
			</entity>
		<entity>
			<id>72@e@doc0057_PATH@gold</id>
			<span>352,369</span>
			<type>Event</type>
			</entity>
		<entity>
			<id>73@e@doc0057_PATH@gold</id>
			<span>435,443</span>
			<type>Event</type>
			</entity>
		<entity>
			<id>74@e@doc0057_PATH@gold</id>
			<span>463,470</span>
			<type>Event</type>
			</entity>
		<entity>
			<id>75@e@doc0057_PATH@gold</id>
			<span>513,521</span>
			<type>Event</type>
			</entity>
		<entity>
			<id>76@e@doc0057_PATH@gold</id>
			<span>527,532</span>
			<type>Event</type>
			</entity>
		<entity>
			<id>77@e@doc0057_PATH@gold</id>
			<span>539,553</span>
			<type>Event</type>
			</entity>
		<entity>
			<id>78@e@doc0057_PATH@gold</id>
			<span>570,573</span>
			<type>Event</type>
			</entity>
		<entity>
			<id>79@e@doc0057_PATH@gold</id>
			<span>605,609</span>
			<type>Event</type>
			</entity>
		<entity>
			<id>80@e@doc0057_PATH@gold</id>
			<span>614,617</span>
			<type>Event</type>
			</entity>
		<entity>
			<id>81@e@doc0057_PATH@gold</id>
			<span>645,649</span>
			<type>Event</type>
			</entity>
		<entity>
			<id>82@e@doc0057_PATH@gold</id>
			<span>669,675</span>
			<type>Event</type>
			</entity>
		<entity>
			<id>83@e@doc0057_PATH@gold</id>
			<span>676,682</span>
			<type>Event</type>
			</entity>
		<entity>
			<id>84@e@doc0057_PATH@gold</id>
			<span>718,725</span>
			<type>Event</type>
			</entity>
		<entity>
			<id>85@e@doc0057_PATH@gold</id>
			<span>729,736</span>
			<type>Event</type>
			</entity>
		<entity>
			<id>86@e@doc0057_PATH@gold</id>
			<span>760,765</span>
			<type>Event</type>
			</entity>
		<entity>
			<id>87@e@doc0057_PATH@gold</id>
			<span>798,803</span>
			<type>Event</type>
			</entity>
		<entity>
			<id>88@e@doc0057_PATH@gold</id>
			<span>824,830</span>
			<type>Event</type>
			</entity>
		<entity>
			<id>89@e@doc0057_PATH@gold</id>
			<span>843,848</span>
			<type>Event</type>
			</entity>
		<entity>
			<id>90@e@doc0057_PATH@gold</id>
			<span>876,881</span>
			<type>Event</type>
			</entity>
		<entity>
			<id>91@e@doc0057_PATH@gold</id>
			<span>900,910</span>
			<type>Event</type>
			</entity>
		<entity>
			<id>92@e@doc0057_PATH@gold</id>
			<span>918,926</span>
			<type>Event</type>
			</entity>
		<entity>
			<id>93@e@doc0057_PATH@gold</id>
			<span>975,982</span>
			<type>Event</type>
			</entity>
		<entity>
			<id>94@e@doc0057_PATH@gold</id>
			<span>987,991</span>
			<type>Event</type>
			</entity>
		<entity>
			<id>96@e@doc0057_PATH@gold</id>
			<span>1026,1035</span>
			<type>Event</type>
			</entity>
		<entity>
			<id>97@e@doc0057_PATH@gold</id>
			<span>1062,1069</span>
			<type>Event</type>
			</entity>
		<entity>
			<id>98@e@doc0057_PATH@gold</id>
			<span>1080,1088</span>
			<type>Event</type>
			</entity>
		<entity>
			<id>99@e@doc0057_PATH@gold</id>
			<span>1107,1116</span>
			<type>Event</type>
			</entity>
		<entity>
			<id>100@e@doc0057_PATH@gold</id>
			<span>1133,1142</span>
			<type>Event</type>
			</entity>
		<entity>
			<id>101@e@doc0057_PATH@gold</id>
			<span>1155,1173</span>
			<type>Event</type>
			</entity>
		<entity>
			<id>102@e@doc0057_PATH@gold</id>
			<span>1185,1189</span>
			<type>Event</type>
			</entity>
		<entity>
			<id>103@e@doc0057_PATH@gold</id>
			<span>1194,1203</span>
			<type>Event</type>
			</entity>
		<entity>
			<id>104@e@doc0057_PATH@gold</id>
			<span>1224,1239</span>
			<type>Event</type>
			</entity>
		<entity>
			<id>105@e@doc0057_PATH@gold</id>
			<span>1242,1252</span>
			<type>Event</type>
			</entity>
		<entity>
			<id>106@e@doc0057_PATH@gold</id>
			<span>1300,1302</span>
			<type>Event</type>
			</entity>
		<entity>
			<id>107@e@doc0057_PATH@gold</id>
			<span>1316,1323</span>
			<type>Event</type>
			</entity>
		<entity>
			<id>108@e@doc0057_PATH@gold</id>
			<span>1327,1335</span>
			<type>Event</type>
			</entity>
		<entity>
			<id>109@e@doc0057_PATH@gold</id>
			<span>1393,1397</span>
			<type>Event</type>
			</entity>
		<entity>
			<id>110@e@doc0057_PATH@gold</id>
			<span>1404,1411</span>
			<type>Event</type>
			</entity>
		<entity>
			<id>111@e@doc0057_PATH@gold</id>
			<span>1452,1463</span>
			<type>Event</type>
			</entity>
		<entity>
			<id>112@e@doc0057_PATH@gold</id>
			<span>1471,1475</span>
			<type>Event</type>
			</entity>
		<entity>
			<id>113@e@doc0057_PATH@gold</id>
			<span>1485,1489</span>
			<type>Event</type>
			</entity>
		<entity>
			<id>114@e@doc0057_PATH@gold</id>
			<span>1513,1522</span>
			<type>Event</type>
			</entity>
		<entity>
			<id>116@e@doc0057_PATH@gold</id>
			<span>1597,1609</span>
			<type>Event</type>
			</entity>
		<entity>
			<id>117@e@doc0057_PATH@gold</id>
			<span>1623,1640</span>
			<type>Event</type>
			</entity>
		<entity>
			<id>118@e@doc0057_PATH@gold</id>
			<span>1643,1647</span>
			<type>Event</type>
			</entity>
		<entity>
			<id>119@e@doc0057_PATH@gold</id>
			<span>1660,1676</span>
			<type>Event</type>
			</entity>
		<entity>
			<id>120@e@doc0057_PATH@gold</id>
			<span>219,226</span>
			<type>Event</type>
			</entity>
		<entity>
			<id>121@e@doc0057_PATH@gold</id>
			<span>318,322</span>
			<type>Event</type>
			</entity>
		<entity>
			<id>123@e@doc0057_PATH@gold</id>
			<span>587,592</span>
			<type>Event</type>
			</entity>
		<entity>
			<id>124@e@doc0057_PATH@gold</id>
			<span>593,600</span>
			<type>Event</type>
			</entity>
		<entity>
			<id>125@e@doc0057_PATH@gold</id>
			<span>628,633</span>
			<type>Event</type>
			</entity>
		<entity>
			<id>126@e@doc0057_PATH@gold</id>
			<span>634,641</span>
			<type>Event</type>
			</entity>
		<entity>
			<id>127@e@doc0057_PATH@gold</id>
			<span>690,697</span>
			<type>Event</type>
			</entity>
		<entity>
			<id>128@e@doc0057_PATH@gold</id>
			<span>1589,1596</span>
			<type>Event</type>
			</entity>
		<entity>
			<id>130@e@doc0057_PATH@gold</id>
			<span>94,102</span>
			<type>Event</type>
			</entity>
		<entity>
			<id>131@e@doc0057_PATH@gold</id>
			<span>167,178</span>
			<type>Event</type>
			</entity>
		<entity>
			<id>132@e@doc0057_PATH@gold</id>
			<span>376,381</span>
			<type>Event</type>
			</entity>
		<entity>
			<id>133@e@doc0057_PATH@gold</id>
			<span>1008,1013</span>
			<type>Event</type>
			</entity>
		<entity>
			<id>134@e@doc0057_PATH@gold</id>
			<span>1041,1043</span>
			<type>Event</type>
			</entity>
		<entity>
			<id>135@e@doc0057_PATH@gold</id>
			<span>1048,1051</span>
			<type>Event</type>
			</entity>
		<entity>
			<id>0@regex</id>
			<type>PreAnnotation</type>
			<span>7,17</span>
		</entity>
		<entity>
			<id>1@regex</id>
			<type>PreAnnotation</type>
			<span>50,54</span>
		</entity>
		<entity>
			<id>2@regex</id>
			<type>PreAnnotation</type>
			<span>149,153</span>
		</entity>
		<entity>
			<id>3@regex</id>
			<type>PreAnnotation</type>
			<span>187,191</span>
		</entity>
		<entity>
			<id>4@regex</id>
			<type>PreAnnotation</type>
			<span>395,404</span>
		</entity>
		<entity>
			<id>5@regex</id>
			<type>PreAnnotation</type>
			<span>424,428</span>
		</entity>
		<entity>
			<id>6@regex</id>
			<type>PreAnnotation</type>
			<span>1527,1537</span>
		</entity>
	</annotations>
</data>
