<?xml version='1.0' encoding='UTF-8'?>
<data>
<info>
  <savetime>13:42:19 14-01-2017</savetime>
  <progress>completed</progress>
</info>

<schema path="./" protocol="file">temporal.schema.xml</schema>

<annotations>
	<entity>
		<id>73@e@ID065_clinic_193@gold</id>
		<span>110,114</span>
		<type>Event</type>
		<parentsType>Other</parentsType>
		<properties>
		</properties>
	</entity>

	<entity>
		<id>75@e@ID065_clinic_193@gold</id>
		<span>168,174</span>
		<type>Event</type>
		<parentsType>Other</parentsType>
		<properties>
		</properties>
	</entity>

	<entity>
		<id>76@e@ID065_clinic_193@gold</id>
		<span>181,188</span>
		<type>Event</type>
		<parentsType>Other</parentsType>
		<properties>
		</properties>
	</entity>

	<entity>
		<id>77@e@ID065_clinic_193@gold</id>
		<span>190,200</span>
		<type>Event</type>
		<parentsType>Other</parentsType>
		<properties>
		</properties>
	</entity>

	<entity>
		<id>78@e@ID065_clinic_193@gold</id>
		<span>206,210</span>
		<type>Event</type>
		<parentsType>Other</parentsType>
		<properties>
		</properties>
	</entity>

	<entity>
		<id>79@e@ID065_clinic_193@gold</id>
		<span>228,236</span>
		<type>Event</type>
		<parentsType>Other</parentsType>
		<properties>
		</properties>
	</entity>

	<entity>
		<id>80@e@ID065_clinic_193@gold</id>
		<span>330,337</span>
		<type>Event</type>
		<parentsType>Other</parentsType>
		<properties>
		</properties>
	</entity>

	<entity>
		<id>81@e@ID065_clinic_193@gold</id>
		<span>342,350</span>
		<type>Event</type>
		<parentsType>Other</parentsType>
		<properties>
		</properties>
	</entity>

	<entity>
		<id>83@e@ID065_clinic_193@gold</id>
		<span>393,402</span>
		<type>Event</type>
		<parentsType>Other</parentsType>
		<properties>
		</properties>
	</entity>

	<entity>
		<id>84@e@ID065_clinic_193@gold</id>
		<span>429,435</span>
		<type>Event</type>
		<parentsType>Other</parentsType>
		<properties>
		</properties>
	</entity>

	<entity>
		<id>85@e@ID065_clinic_193@gold</id>
		<span>455,461</span>
		<type>Event</type>
		<parentsType>Other</parentsType>
		<properties>
		</properties>
	</entity>

	<entity>
		<id>86@e@ID065_clinic_193@gold</id>
		<span>483,492</span>
		<type>Event</type>
		<parentsType>Other</parentsType>
		<properties>
		</properties>
	</entity>

	<entity>
		<id>87@e@ID065_clinic_193@gold</id>
		<span>497,504</span>
		<type>Event</type>
		<parentsType>Other</parentsType>
		<properties>
		</properties>
	</entity>

	<entity>
		<id>88@e@ID065_clinic_193@gold</id>
		<span>536,544</span>
		<type>Event</type>
		<parentsType>Other</parentsType>
		<properties>
		</properties>
	</entity>

	<entity>
		<id>89@e@ID065_clinic_193@gold</id>
		<span>605,615</span>
		<type>Event</type>
		<parentsType>Other</parentsType>
		<properties>
		</properties>
	</entity>

	<entity>
		<id>90@e@ID065_clinic_193@gold</id>
		<span>645,649</span>
		<type>Event</type>
		<parentsType>Other</parentsType>
		<properties>
		</properties>
	</entity>

	<entity>
		<id>91@e@ID065_clinic_193@gold</id>
		<span>661,668</span>
		<type>Event</type>
		<parentsType>Other</parentsType>
		<properties>
		</properties>
	</entity>

	<entity>
		<id>92@e@ID065_clinic_193@gold</id>
		<span>692,705</span>
		<type>Event</type>
		<parentsType>Other</parentsType>
		<properties>
		</properties>
	</entity>

	<entity>
		<id>93@e@ID065_clinic_193@gold</id>
		<span>721,729</span>
		<type>Event</type>
		<parentsType>Other</parentsType>
		<properties>
		</properties>
	</entity>

	<entity>
		<id>94@e@ID065_clinic_193@gold</id>
		<span>730,736</span>
		<type>Event</type>
		<parentsType>Other</parentsType>
		<properties>
		</properties>
	</entity>

	<entity>
		<id>95@e@ID065_clinic_193@gold</id>
		<span>742,756</span>
		<type>Event</type>
		<parentsType>Other</parentsType>
		<properties>
		</properties>
	</entity>

	<entity>
		<id>96@e@ID065_clinic_193@gold</id>
		<span>765,776</span>
		<type>Event</type>
		<parentsType>Other</parentsType>
		<properties>
		</properties>
	</entity>

	<entity>
		<id>97@e@ID065_clinic_193@gold</id>
		<span>846,854</span>
		<type>Event</type>
		<parentsType>Other</parentsType>
		<properties>
		</properties>
	</entity>

	<entity>
		<id>98@e@ID065_clinic_193@gold</id>
		<span>858,867</span>
		<type>Event</type>
		<parentsType>Other</parentsType>
		<properties>
		</properties>
	</entity>

	<entity>
		<id>99@e@ID065_clinic_193@gold</id>
		<span>918,922</span>
		<type>Event</type>
		<parentsType>Other</parentsType>
		<properties>
		</properties>
	</entity>

	<entity>
		<id>100@e@ID065_clinic_193@gold</id>
		<span>984,990</span>
		<type>Event</type>
		<parentsType>Other</parentsType>
		<properties>
		</properties>
	</entity>

	<entity>
		<id>101@e@ID065_clinic_193@gold</id>
		<span>994,1002</span>
		<type>Event</type>
		<parentsType>Other</parentsType>
		<properties>
		</properties>
	</entity>

	<entity>
		<id>102@e@ID065_clinic_193@gold</id>
		<span>1012,1019</span>
		<type>Event</type>
		<parentsType>Other</parentsType>
		<properties>
		</properties>
	</entity>

	<entity>
		<id>103@e@ID065_clinic_193@gold</id>
		<span>1052,1059</span>
		<type>Event</type>
		<parentsType>Other</parentsType>
		<properties>
		</properties>
	</entity>

	<entity>
		<id>104@e@ID065_clinic_193@gold</id>
		<span>1100,1103</span>
		<type>Event</type>
		<parentsType>Other</parentsType>
		<properties>
		</properties>
	</entity>

	<entity>
		<id>105@e@ID065_clinic_193@gold</id>
		<span>1121,1131</span>
		<type>Event</type>
		<parentsType>Other</parentsType>
		<properties>
		</properties>
	</entity>

	<entity>
		<id>106@e@ID065_clinic_193@gold</id>
		<span>1170,1179</span>
		<type>Event</type>
		<parentsType>Other</parentsType>
		<properties>
		</properties>
	</entity>

	<entity>
		<id>107@e@ID065_clinic_193@gold</id>
		<span>1187,1200</span>
		<type>Event</type>
		<parentsType>Other</parentsType>
		<properties>
		</properties>
	</entity>

	<entity>
		<id>108@e@ID065_clinic_193@gold</id>
		<span>1244,1250</span>
		<type>Event</type>
		<parentsType>Other</parentsType>
		<properties>
		</properties>
	</entity>

	<entity>
		<id>109@e@ID065_clinic_193@gold</id>
		<span>1266,1275</span>
		<type>Event</type>
		<parentsType>Other</parentsType>
		<properties>
		</properties>
	</entity>

	<entity>
		<id>110@e@ID065_clinic_193@gold</id>
		<span>1290,1300</span>
		<type>Event</type>
		<parentsType>Other</parentsType>
		<properties>
		</properties>
	</entity>

	<entity>
		<id>111@e@ID065_clinic_193@gold</id>
		<span>1330,1339</span>
		<type>Event</type>
		<parentsType>Other</parentsType>
		<properties>
		</properties>
	</entity>

	<entity>
		<id>112@e@ID065_clinic_193@gold</id>
		<span>1390,1403</span>
		<type>Event</type>
		<parentsType>Other</parentsType>
		<properties>
		</properties>
	</entity>

	<entity>
		<id>114@e@ID065_clinic_193@gold</id>
		<span>1423,1431</span>
		<type>Event</type>
		<parentsType>Other</parentsType>
		<properties>
		</properties>
	</entity>

	<entity>
		<id>115@e@ID065_clinic_193@gold</id>
		<span>1440,1447</span>
		<type>Event</type>
		<parentsType>Other</parentsType>
		<properties>
		</properties>
	</entity>

	<entity>
		<id>116@e@ID065_clinic_193@gold</id>
		<span>1509,1515</span>
		<type>Event</type>
		<parentsType>Other</parentsType>
		<properties>
		</properties>
	</entity>

	<entity>
		<id>117@e@ID065_clinic_193@gold</id>
		<span>1551,1561</span>
		<type>Event</type>
		<parentsType>Other</parentsType>
		<properties>
		</properties>
	</entity>

	<entity>
		<id>118@e@ID065_clinic_193@gold</id>
		<span>1657,1667</span>
		<type>Event</type>
		<parentsType>Other</parentsType>
		<properties>
		</properties>
	</entity>

	<entity>
		<id>119@e@ID065_clinic_193@gold</id>
		<span>1702,1708</span>
		<type>Event</type>
		<parentsType>Other</parentsType>
		<properties>
		</properties>
	</entity>

	<entity>
		<id>120@e@ID065_clinic_193@gold</id>
		<span>2045,2051</span>
		<type>Event</type>
		<parentsType>Other</parentsType>
		<properties>
		</properties>
	</entity>

	<entity>
		<id>121@e@ID065_clinic_193@gold</id>
		<span>2223,2229</span>
		<type>Event</type>
		<parentsType>Other</parentsType>
		<properties>
		</properties>
	</entity>

	<entity>
		<id>122@e@ID065_clinic_193@gold</id>
		<span>311,315</span>
		<type>Event</type>
		<parentsType>Other</parentsType>
		<properties>
		</properties>
	</entity>

	<entity>
		<id>123@e@ID065_clinic_193@gold</id>
		<span>115,127</span>
		<type>Event</type>
		<parentsType>Other</parentsType>
		<properties>
		</properties>
	</entity>

	<entity>
		<id>124@e@ID065_clinic_193@gold</id>
		<span>251,255</span>
		<type>Event</type>
		<parentsType>Other</parentsType>
		<properties>
		</properties>
	</entity>

	<entity>
		<id>125@e@ID065_clinic_193@gold</id>
		<span>296,307</span>
		<type>Event</type>
		<parentsType>Other</parentsType>
		<properties>
		</properties>
	</entity>

	<entity>
		<id>126@e@ID065_clinic_193@gold</id>
		<span>358,368</span>
		<type>Event</type>
		<parentsType>Other</parentsType>
		<properties>
		</properties>
	</entity>

	<entity>
		<id>127@e@ID065_clinic_193@gold</id>
		<span>555,563</span>
		<type>Event</type>
		<parentsType>Other</parentsType>
		<properties>
		</properties>
	</entity>

	<entity>
		<id>128@e@ID065_clinic_193@gold</id>
		<span>581,589</span>
		<type>Event</type>
		<parentsType>Other</parentsType>
		<properties>
		</properties>
	</entity>

	<entity>
		<id>129@e@ID065_clinic_193@gold</id>
		<span>594,598</span>
		<type>Event</type>
		<parentsType>Other</parentsType>
		<properties>
		</properties>
	</entity>

	<entity>
		<id>130@e@ID065_clinic_193@gold</id>
		<span>927,937</span>
		<type>Event</type>
		<parentsType>Other</parentsType>
		<properties>
		</properties>
	</entity>

	<entity>
		<id>131@e@ID065_clinic_193@gold</id>
		<span>1072,1084</span>
		<type>Event</type>
		<parentsType>Other</parentsType>
		<properties>
		</properties>
	</entity>

	<entity>
		<id>132@e@ID065_clinic_193@gold</id>
		<span>1152,1158</span>
		<type>Event</type>
		<parentsType>Other</parentsType>
		<properties>
		</properties>
	</entity>

	<entity>
		<id>133@e@ID065_clinic_193@gold</id>
		<span>1208,1218</span>
		<type>Event</type>
		<parentsType>Other</parentsType>
		<properties>
		</properties>
	</entity>

	<entity>
		<id>135@e@ID065_clinic_193@gold</id>
		<span>1251,1260</span>
		<type>Event</type>
		<parentsType>Other</parentsType>
		<properties>
		</properties>
	</entity>

	<entity>
		<id>136@e@ID065_clinic_193@gold</id>
		<span>1304,1317</span>
		<type>Event</type>
		<parentsType>Other</parentsType>
		<properties>
		</properties>
	</entity>

	<entity>
		<id>137@e@ID065_clinic_193@gold</id>
		<span>1543,1550</span>
		<type>Event</type>
		<parentsType>Other</parentsType>
		<properties>
		</properties>
	</entity>

	<entity>
		<id>138@e@ID065_clinic_193@gold</id>
		<span>1621,1625</span>
		<type>Event</type>
		<parentsType>Other</parentsType>
		<properties>
		</properties>
	</entity>

	<entity>
		<id>139@e@ID065_clinic_193@gold</id>
		<span>1712,1716</span>
		<type>Event</type>
		<parentsType>Other</parentsType>
		<properties>
		</properties>
	</entity>

	<entity>
		<id>153@e@ID065_clinic_193@gold</id>
		<span>128,133</span>
		<type>This</type>
		<parentsType>Operator</parentsType>
		<properties>
			<Interval-Type>DocTime</Interval-Type>
			<Interval></Interval>
			<Period></Period>
			<Repeating-Interval>160@e@ID065_clinic_193@gold</Repeating-Interval>
		</properties>
	</entity>

	<entity>
		<id>154@e@ID065_clinic_193@gold</id>
		<span>16,18</span>
		<type>Month-Of-Year</type>
		<parentsType>Repeating-Interval</parentsType>
		<properties>
			<Type>August</Type>
			<Sub-Interval>159@e@ID065_clinic_193@gold</Sub-Interval>
			<Number></Number>
			<Modifier></Modifier>
		</properties>
	</entity>

	<entity>
		<id>155@e@ID065_clinic_193@gold</id>
		<span>1408,1412</span>
		<type>This</type>
		<parentsType>Operator</parentsType>
		<properties>
			<Interval-Type>DocTime</Interval-Type>
			<Interval></Interval>
			<Period>162@e@ID065_clinic_193@gold</Period>
			<Repeating-Interval></Repeating-Interval>
		</properties>
	</entity>

	<entity>
		<id>156@e@ID065_clinic_193@gold</id>
		<span>40,42</span>
		<type>Month-Of-Year</type>
		<parentsType>Repeating-Interval</parentsType>
		<properties>
			<Type>August</Type>
			<Sub-Interval>157@e@ID065_clinic_193@gold</Sub-Interval>
			<Number></Number>
			<Modifier></Modifier>
		</properties>
	</entity>

	<entity>
		<id>157@e@ID065_clinic_193@gold</id>
		<span>43,45</span>
		<type>Day-Of-Month</type>
		<parentsType>Repeating-Interval</parentsType>
		<properties>
			<Value>11</Value>
			<Sub-Interval></Sub-Interval>
			<Number></Number>
			<Modifier></Modifier>
		</properties>
	</entity>

	<entity>
		<id>158@e@ID065_clinic_193@gold</id>
		<span>625,630</span>
		<type>Period</type>
		<parentsType>Duration</parentsType>
		<properties>
			<Type>Unknown</Type>
			<Number></Number>
			<Modifier></Modifier>
		</properties>
	</entity>

	<entity>
		<id>159@e@ID065_clinic_193@gold</id>
		<span>19,21</span>
		<type>Day-Of-Month</type>
		<parentsType>Repeating-Interval</parentsType>
		<properties>
			<Value>11</Value>
			<Sub-Interval></Sub-Interval>
			<Number></Number>
			<Modifier></Modifier>
		</properties>
	</entity>

	<entity>
		<id>160@e@ID065_clinic_193@gold</id>
		<span>128,133</span>
		<type>Calendar-Interval</type>
		<parentsType>Repeating-Interval</parentsType>
		<properties>
			<Type>Day</Type>
			<Number></Number>
			<Modifier></Modifier>
		</properties>
	</entity>

	<entity>
		<id>161@e@ID065_clinic_193@gold</id>
		<span>384,392</span>
		<type>Last</type>
		<parentsType>Operator</parentsType>
		<properties>
			<Semantics>Interval-Not-Included</Semantics>
			<Interval-Type>DocTime</Interval-Type>
			<Interval></Interval>
			<Period></Period>
			<Repeating-Interval></Repeating-Interval>
		</properties>
	</entity>

	<entity>
		<id>162@e@ID065_clinic_193@gold</id>
		<span>1413,1418</span>
		<type>Period</type>
		<parentsType>Duration</parentsType>
		<properties>
			<Type>Unknown</Type>
			<Number></Number>
			<Modifier></Modifier>
		</properties>
	</entity>

	<entity>
		<id>163@e@ID065_clinic_193@gold</id>
		<span>46,50</span>
		<type>Year</type>
		<parentsType>Interval</parentsType>
		<properties>
			<Value>2010</Value>
			<Sub-Interval>156@e@ID065_clinic_193@gold</Sub-Interval>
			<Modifier></Modifier>
		</properties>
	</entity>

	<entity>
		<id>164@e@ID065_clinic_193@gold</id>
		<span>22,26</span>
		<type>Year</type>
		<parentsType>Interval</parentsType>
		<properties>
			<Value>2010</Value>
			<Sub-Interval>154@e@ID065_clinic_193@gold</Sub-Interval>
			<Modifier></Modifier>
		</properties>
	</entity>

	<entity>
		<id>165@e@ID065_clinic_193@gold</id>
		<span>411,416</span>
		<type>Modifier</type>
		<parentsType>Other</parentsType>
		<properties>
			<Type>Start</Type>
		</properties>
	</entity>

</annotations>

</data>